setup.cfg
setup.py
birdpy/__init__.py
birdpy/cherrypy_helpers.py
birdpy/classes.py
birdpy/helpers.py
birdpy/jinja2_filters.py
birdpy/jinja2_helpers.py
birdpy.egg-info/PKG-INFO
birdpy.egg-info/SOURCES.txt
birdpy.egg-info/dependency_links.txt
birdpy.egg-info/top_level.txt