Metadata-Version: 1.1
Name: birdpy
Version: 0.7.2
Summary: Helper functions for python, cherrypy, jinja2, and more!
Home-page: https://pypi.python.org/pypi/birdpy
Author: Anthony Casagrande
Author-email: birdapi@gmail.com
License: MIT
Keywords: birdapi
Platform: UNKNOWN
Classifier: Development Status :: 4 - Beta
Classifier: Programming Language :: Python :: 2.7
Classifier: License :: OSI Approved :: MIT License
